pytaintx/__init__.py
pytaintx/__main__.py
pytaintx/analysis/__init__.py
pytaintx/analysis/constraint_table.py
pytaintx/analysis/definition_chains.py
pytaintx/analysis/fixed_point.py
pytaintx/analysis/lattice.py
pytaintx/analysis/reaching_definitions_taint.py
pytaintx/analysis/README.rst
pytaintx/cfg/__init__.py
pytaintx/cfg/alias_helper.py
pytaintx/cfg/expr_visitor.py
pytaintx/cfg/expr_visitor_helper.py
pytaintx/cfg/make_cfg.py
pytaintx/cfg/README.rst
pytaintx/cfg/stmt_visitor.py
pytaintx/cfg/stmt_visitor_helper.py
pytaintx/core/__init__.py
pytaintx/core/ast_helper.py
pytaintx/core/module_definitions.py
pytaintx/core/node_types.py
pytaintx/core/project_handler.py
pytaintx/core/README.rst
pytaintx/core/transformer.py
pytaintx/formatters/__init__.py
pytaintx/formatters/json.py
pytaintx/formatters/screen.py
pytaintx/formatters/text.py
pytaintx/helper_visitors/__init__.py
pytaintx/helper_visitors/call_visitor.py
pytaintx/helper_visitors/label_visitor.py
pytaintx/helper_visitors/README.rst
pytaintx/helper_visitors/right_hand_side_visitor.py
pytaintx/helper_visitors/vars_visitor.py
pytaintx/README.rst
pytaintx/usage.py
pytaintx/vulnerabilities/__init__.py
pytaintx/vulnerabilities/README.rst
pytaintx/vulnerabilities/trigger_definitions_parser.py
pytaintx/vulnerabilities/vulnerabilities.py
pytaintx/vulnerabilities/vulnerability_helper.py
pytaintx/vulnerability_definitions/all_trigger_words.pyt
pytaintx/vulnerability_definitions/blackbox_mapping.json
pytaintx/vulnerability_definitions/django_trigger_words.pyt
pytaintx/vulnerability_definitions/flask_trigger_words.pyt
pytaintx/vulnerability_definitions/README.rst
pytaintx/vulnerability_definitions/test_positions.pyt
pytaintx/vulnerability_definitions/test_triggers.pyt
pytaintx/web_frameworks/__init__.py
pytaintx/web_frameworks/framework_adaptor.py
pytaintx/web_frameworks/framework_helper.py
pytaintx/web_frameworks/README.rst
pytaintx-0.5.2.dist-info/entry_points.txt
pytaintx-0.5.2.dist-info/LICENSE
pytaintx-0.5.2.dist-info/WHEEL
pytaintx-0.5.2.dist-info/METADATA
pytaintx-0.5.2.dist-info/RECORD
