Metadata-Version: 2.1
Name: pytaintx
Version: 0.5.2
Summary: Find security vulnerabilities in Python web applications
Home-page: https://github.com/FHPythonUtils/pytaintx
License: GPLv2
Requires-Python: >=3.7,<4.0
Classifier: Development Status :: 3 - Alpha
Classifier: Intended Audience :: Developers
Classifier: Intended Audience :: Science/Research
Classifier: License :: OSI Approved :: GNU General Public License v2 (GPLv2)
Classifier: License :: Other/Proprietary License
Classifier: Natural Language :: English
Classifier: Operating System :: OS Independent
Classifier: Programming Language :: Python :: 3
Classifier: Programming Language :: Python :: 3.7
Classifier: Programming Language :: Python :: 3.8
Classifier: Programming Language :: Python :: 3.9
Classifier: Topic :: Scientific/Engineering
Classifier: Topic :: Security
Classifier: Topic :: Software Development
Classifier: Topic :: Utilities
Project-URL: Documentation, https://github.com/FHPythonUtils/pytaintx/blob/master/README.md
Project-URL: Repository, https://github.com/FHPythonUtils/pytaintx
